ChainEngine/__init__.py
ChainEngine/pychain.py
ChainEngine-2.4.dist-info/METADATA
ChainEngine-2.4.dist-info/WHEEL
ChainEngine-2.4.dist-info/top_level.txt
ChainEngine-2.4.dist-info/RECORD
